setup.py
aboardly/__init__.py
aboardly/aboardly.py
aboardly/customers.py
aboardly/events.py
aboardly.egg-info/PKG-INFO
aboardly.egg-info/SOURCES.txt
aboardly.egg-info/dependency_links.txt
aboardly.egg-info/requires.txt
aboardly.egg-info/top_level.txt