Metadata-Version: 1.1
Name: aboardly
Version: 0.1.1
Summary: Official Aboardly API library client for python
Home-page: https://github.com/landland/aboardly-python
Author: Martin
Author-email: info@aboardly.com
License: MIT
Download-URL: https://github.com/landland/aboardly-python/tarball/0.1.1
Platform: UNKNOWN
Classifier: Development Status :: 5 - Production/Stable
Classifier: Intended Audience :: Developers
Classifier: License :: OSI Approved :: MIT License
Classifier: Operating System :: OS Independent
Classifier: Programming Language :: Python :: 2.6
Classifier: Programming Language :: Python :: 2.7
Classifier: Programming Language :: Python :: 3.2
Classifier: Programming Language :: Python :: 3.3
Classifier: Topic :: Software Development :: Libraries :: Python Modules
